knipse.py
knipse-0.8.0.data/data/HISTORY.md
knipse-0.8.0.data/data/LICENSE
knipse-0.8.0.dist-info/LICENSE
knipse-0.8.0.dist-info/METADATA
knipse-0.8.0.dist-info/WHEEL
knipse-0.8.0.dist-info/entry_points.txt
knipse-0.8.0.dist-info/top_level.txt
knipse-0.8.0.dist-info/zip-safe
knipse-0.8.0.dist-info/RECORD
