Metadata-Version: 2.1
Name: knipse
Version: 0.8.0
Summary: CLI catalog manager for pix and gThumb
Home-page: https://github.com/luphord/knipse
Author: luphord
Author-email: luphord@protonmail.com
License: MIT license
Keywords: knipse
Classifier: Development Status :: 2 - Pre-Alpha
Classifier: Intended Audience :: Developers
Classifier: License :: OSI Approved :: MIT License
Classifier: Natural Language :: English
Classifier: Programming Language :: Python :: 3
Classifier: Programming Language :: Python :: 3.8
Classifier: Programming Language :: Python :: 3.9
Classifier: Programming Language :: Python :: 3.10
Classifier: Programming Language :: Python :: 3.11
Requires-Python: >=3.8
License-File: LICENSE
